{
    "version": "0.4",
    "title": "FAQ",
    "type": "page",
    "metadata": {
        "template_type": "single-page",
        "include_in_zip": "1",
        "elementor_pro_required": null,
        "wp_page_template": "elementor_header_footer"
    },
    "content": [
        {
            "id": "3bbdf936",
            "settings": {
                "height": "min-height",
                "custom_height": {
                    "unit": "px",
                    "size": 500,
                    "sizes": []
                },
                "background_background": "classic",
                "background_overlay_background": "classic",
                "background_overlay_image": {
                    "url": "http:\/\/gnome.welearn2fly.com\/wp-content\/uploads\/2021\/03\/lawn-37.jpg",
                    "id": 5344
                },
                "background_overlay_repeat": "no-repeat",
                "__globals__": {
                    "background_color": "globals\/colors?id=8c9d710"
                },
                "custom_height_tablet": {
                    "unit": "px",
                    "size": 350,
                    "sizes": []
                }
            },
            "elements": [
                {
                    "id": "6da0fb37",
                    "settings": {
                        "_column_size": 100,
                        "_inline_size": null
                    },
                    "elements": [
                        {
                            "id": "7dcca782",
                            "settings": {
                                "title": "FAQ",
                                "__globals__": {
                                    "typography_typography": "",
                                    "title_color": "globals\/colors?id=secondary"
                                },
                                "align": "center"
                            },
                            "elements": [],
                            "isInner": false,
                            "widgetType": "heading",
                            "elType": "widget"
                        }
                    ],
                    "isInner": false,
                    "elType": "column"
                }
            ],
            "isInner": false,
            "elType": "section"
        },
        {
            "id": "4460c40d",
            "settings": {
                "structure": "20",
                "background_background": "classic",
                "margin": {
                    "unit": "px",
                    "top": "0",
                    "right": 0,
                    "bottom": "0",
                    "left": 0,
                    "isLinked": false
                },
                "padding": {
                    "unit": "px",
                    "top": "80",
                    "right": "0",
                    "bottom": "30",
                    "left": "0",
                    "isLinked": false
                },
                "__globals__": {
                    "background_color": ""
                },
                "padding_tablet": {
                    "unit": "px",
                    "top": "50",
                    "right": "0",
                    "bottom": "0",
                    "left": "0",
                    "isLinked": false
                }
            },
            "elements": [
                {
                    "id": "77aef489",
                    "settings": {
                        "_column_size": 50,
                        "_inline_size": 60,
                        "_inline_size_tablet": 100,
                        "padding_tablet": {
                            "unit": "px",
                            "top": "30",
                            "right": "0",
                            "bottom": "0",
                            "left": "0",
                            "isLinked": false
                        },
                        "margin_tablet": {
                            "unit": "px",
                            "top": "30",
                            "right": "30",
                            "bottom": "30",
                            "left": "30",
                            "isLinked": true
                        },
                        "margin_mobile": {
                            "unit": "px",
                            "top": "10",
                            "right": "10",
                            "bottom": "10",
                            "left": "10",
                            "isLinked": true
                        }
                    },
                    "elements": [
                        {
                            "id": "11ff672c",
                            "settings": {
                                "title": "Lawn & Garden Services",
                                "title_color": "#6AB42E",
                                "__globals__": {
                                    "title_color": "globals\/colors?id=accent",
                                    "typography_typography": ""
                                },
                                "header_size": "h4",
                                "_animation": "fadeInDown",
                                "align_tablet": "left",
                                "align_mobile": "left"
                            },
                            "elements": [],
                            "isInner": false,
                            "widgetType": "heading",
                            "elType": "widget"
                        },
                        {
                            "id": "5701544f",
                            "settings": {
                                "title": "Common Question",
                                "__globals__": {
                                    "typography_typography": "",
                                    "title_color": ""
                                },
                                "_animation": "fadeInDown",
                                "header_size": "h3",
                                "typography_font_size_tablet": {
                                    "unit": "px",
                                    "size": 40,
                                    "sizes": []
                                },
                                "typography_font_size_mobile": {
                                    "unit": "px",
                                    "size": 30,
                                    "sizes": []
                                },
                                "typography_font_weight": "700",
                                "typography_font_style": "normal",
                                "typography_line_height_tablet": {
                                    "unit": "em",
                                    "size": 1.2,
                                    "sizes": []
                                },
                                "typography_line_height_mobile": {
                                    "unit": "em",
                                    "size": 1.2,
                                    "sizes": []
                                },
                                "align_tablet": "left",
                                "align_mobile": "left"
                            },
                            "elements": [],
                            "isInner": false,
                            "widgetType": "heading",
                            "elType": "widget"
                        },
                        {
                            "id": "32da6197",
                            "settings": {
                                "tabs": [
                                    {
                                        "tab_title": "1. Bacon ipsum dolor amet venison",
                                        "tab_content": "<p>The bedding was hardly able to cover it and seemed ready to slide off any moment. His many legs. One morning, when Gregor Samsa woke from troubled dreams, he found himself transformed in his bed into a horrible vermin.<\/p>",
                                        "_id": "ca7f850"
                                    },
                                    {
                                        "tab_title": "2. Hamburger boudin sirloin pancetta biltong ball tip",
                                        "tab_content": "Lorem ipsum dolor sit amet, consectetur adipiscing elit. Ut elit tellus, luctus nec ullamcorper mattis, pulvinar dapibus leo.",
                                        "_id": "c87504d"
                                    },
                                    {
                                        "tab_title": "3. Brisket bacon venison pig fatback kielbasa",
                                        "tab_content": "Lorem ipsum dolor sit amet, consectetur adipiscing elit. Ut elit tellus, luctus nec ullamcorper mattis, pulvinar dapibus leo.",
                                        "_id": "55e96d1"
                                    },
                                    {
                                        "tab_title": "4. Chicken venison turducken salami pig",
                                        "tab_content": "<p>The bedding was hardly able to cover it and seemed ready to slide off any moment. His many legs. One morning, when Gregor Samsa woke from troubled dreams, he found himself transformed in his bed into a horrible vermin.<\/p>",
                                        "_id": "53ded94"
                                    }
                                ],
                                "icon_align": "right",
                                "_margin": {
                                    "unit": "px",
                                    "top": "20",
                                    "right": "0",
                                    "bottom": "0",
                                    "left": "0",
                                    "isLinked": false
                                },
                                "__globals__": {
                                    "title_color": "globals\/colors?id=primary",
                                    "icon_color": "globals\/colors?id=accent",
                                    "icon_active_color": "globals\/colors?id=accent"
                                },
                                "_animation": "fadeInDown"
                            },
                            "elements": [],
                            "isInner": false,
                            "widgetType": "accordion",
                            "elType": "widget"
                        }
                    ],
                    "isInner": false,
                    "elType": "column"
                },
                {
                    "id": "607736e2",
                    "settings": {
                        "_column_size": 50,
                        "_inline_size": 40,
                        "_inline_size_tablet": 100,
                        "_inline_size_mobile": 100,
                        "animation": "fadeIn",
                        "animation_duration": "slow"
                    },
                    "elements": [
                        {
                            "id": "702637cc",
                            "settings": {
                                "carousel": [
                                    {
                                        "id": 5313,
                                        "url": "http:\/\/gnome.welearn2fly.com\/wp-content\/uploads\/2021\/02\/lawn-26.jpg"
                                    },
                                    {
                                        "id": 5315,
                                        "url": "http:\/\/gnome.welearn2fly.com\/wp-content\/uploads\/2021\/02\/lawn-28.jpg"
                                    },
                                    {
                                        "id": 5314,
                                        "url": "http:\/\/gnome.welearn2fly.com\/wp-content\/uploads\/2021\/02\/lawn-27.jpg"
                                    }
                                ],
                                "thumbnail_size": "full",
                                "slides_to_show": "1",
                                "__globals__": {
                                    "arrows_color": "globals\/colors?id=secondary"
                                },
                                "slides_to_show_tablet": "1"
                            },
                            "elements": [],
                            "isInner": false,
                            "widgetType": "image-carousel",
                            "elType": "widget"
                        }
                    ],
                    "isInner": false,
                    "elType": "column"
                }
            ],
            "isInner": false,
            "elType": "section"
        },
        {
            "id": "77be50b8",
            "settings": {
                "padding": {
                    "unit": "px",
                    "top": "0",
                    "right": "0",
                    "bottom": "50",
                    "left": "0",
                    "isLinked": false
                },
                "animation": "fadeInDown",
                "margin_tablet": {
                    "unit": "px",
                    "top": "",
                    "right": 0,
                    "bottom": "",
                    "left": 0,
                    "isLinked": true
                },
                "padding_tablet": {
                    "unit": "px",
                    "top": "30",
                    "right": "0",
                    "bottom": "30",
                    "left": "0",
                    "isLinked": false
                }
            },
            "elements": [
                {
                    "id": "1ea72ce0",
                    "settings": {
                        "_column_size": 100,
                        "_inline_size": null
                    },
                    "elements": [
                        {
                            "id": "456577",
                            "settings": {
                                "carousel": [
                                    {
                                        "id": 5316,
                                        "url": "http:\/\/gnome.welearn2fly.com\/wp-content\/uploads\/2021\/02\/lawn-20.jpg"
                                    },
                                    {
                                        "id": 5317,
                                        "url": "http:\/\/gnome.welearn2fly.com\/wp-content\/uploads\/2021\/02\/lawn-21.jpg"
                                    },
                                    {
                                        "id": 5318,
                                        "url": "http:\/\/gnome.welearn2fly.com\/wp-content\/uploads\/2021\/02\/lawn-22.jpg"
                                    },
                                    {
                                        "id": 5319,
                                        "url": "http:\/\/gnome.welearn2fly.com\/wp-content\/uploads\/2021\/02\/lawn-23-1.jpg"
                                    },
                                    {
                                        "id": 5321,
                                        "url": "http:\/\/gnome.welearn2fly.com\/wp-content\/uploads\/2021\/02\/lawn-25.jpg"
                                    },
                                    {
                                        "id": 5320,
                                        "url": "http:\/\/gnome.welearn2fly.com\/wp-content\/uploads\/2021\/02\/lawn-24.jpg"
                                    }
                                ],
                                "thumbnail_size": "full",
                                "slides_to_show": "3",
                                "navigation": "arrows",
                                "autoplay_speed": 3000,
                                "speed": 400,
                                "image_spacing": "custom",
                                "__globals__": {
                                    "arrows_color": "globals\/colors?id=secondary"
                                }
                            },
                            "elements": [],
                            "isInner": false,
                            "widgetType": "image-carousel",
                            "elType": "widget"
                        }
                    ],
                    "isInner": false,
                    "elType": "column"
                }
            ],
            "isInner": false,
            "elType": "section"
        },
        {
            "id": "55b8fdb3",
            "settings": {
                "padding": {
                    "unit": "px",
                    "top": "0",
                    "right": "0",
                    "bottom": "100",
                    "left": "0",
                    "isLinked": false
                }
            },
            "elements": [
                {
                    "id": "3071d6e6",
                    "settings": {
                        "_column_size": 100,
                        "_inline_size": null
                    },
                    "elements": [
                        {
                            "id": "51e2ddce",
                            "settings": {
                                "title": "Question & answers",
                                "title_color": "#6AB42E",
                                "__globals__": {
                                    "title_color": "globals\/colors?id=accent",
                                    "typography_typography": ""
                                },
                                "header_size": "h4",
                                "_animation": "fadeInDown",
                                "align_tablet": "left"
                            },
                            "elements": [],
                            "isInner": false,
                            "widgetType": "heading",
                            "elType": "widget"
                        },
                        {
                            "id": "4f8c78d8",
                            "settings": {
                                "title": "Common Question",
                                "__globals__": {
                                    "typography_typography": "",
                                    "title_color": ""
                                },
                                "_animation": "fadeInDown",
                                "header_size": "h3",
                                "typography_font_size_tablet": {
                                    "unit": "px",
                                    "size": 40,
                                    "sizes": []
                                },
                                "typography_font_size_mobile": {
                                    "unit": "px",
                                    "size": 30,
                                    "sizes": []
                                },
                                "typography_font_weight": "700",
                                "typography_font_style": "normal",
                                "typography_line_height_tablet": {
                                    "unit": "em",
                                    "size": 1.2,
                                    "sizes": []
                                },
                                "typography_line_height_mobile": {
                                    "unit": "em",
                                    "size": 1.2,
                                    "sizes": []
                                },
                                "align_tablet": "left",
                                "align_mobile": "left"
                            },
                            "elements": [],
                            "isInner": false,
                            "widgetType": "heading",
                            "elType": "widget"
                        },
                        {
                            "id": "778d9b3b",
                            "settings": {
                                "editor": "<p>Lorem ipsum dolor sit amet, consectetur adipiscing elit, sed do eiusmod tempor incididunt ut labore et dolore magna aliqua. Ut enim ad minim veniam, quis nostrud exercitation ullamco laboris nisi ut aliquip .<\/p>",
                                "__globals__": {
                                    "typography_typography": "",
                                    "text_color": ""
                                },
                                "_animation": "fadeInDown",
                                "typography_font_family": "Poppins",
                                "typography_font_size": {
                                    "unit": "px",
                                    "size": 16,
                                    "sizes": []
                                },
                                "typography_font_size_tablet": {
                                    "unit": "px",
                                    "size": 16,
                                    "sizes": []
                                },
                                "typography_font_size_mobile": {
                                    "unit": "px",
                                    "size": 14,
                                    "sizes": []
                                },
                                "typography_font_weight": "400",
                                "typography_line_height_tablet": {
                                    "unit": "em",
                                    "size": 1.6,
                                    "sizes": []
                                },
                                "typography_line_height_mobile": {
                                    "unit": "em",
                                    "size": 1.5,
                                    "sizes": []
                                }
                            },
                            "elements": [],
                            "isInner": false,
                            "widgetType": "text-editor",
                            "elType": "widget"
                        },
                        {
                            "id": "2825cd1c",
                            "settings": {
                                "structure": "20",
                                "animation": "fadeInDown"
                            },
                            "elements": [
                                {
                                    "id": "6a4f363c",
                                    "settings": {
                                        "_column_size": 50,
                                        "_inline_size": null,
                                        "_inline_size_tablet": 100
                                    },
                                    "elements": [
                                        {
                                            "id": "5b5c4ca6",
                                            "settings": {
                                                "tabs": [
                                                    {
                                                        "tab_title": "1. Bacon ipsum dolor amet venison",
                                                        "tab_content": "Lorem ipsum dolor sit amet, consectetur adipiscing elit. Ut elit tellus, luctus nec ullamcorper mattis, pulvinar dapibus leo.",
                                                        "_id": "63f635d"
                                                    },
                                                    {
                                                        "tab_title": "2. Hamburger boudin sirloin pancetta biltong ball tip",
                                                        "tab_content": "Lorem ipsum dolor sit amet, consectetur adipiscing elit. Ut elit tellus, luctus nec ullamcorper mattis, pulvinar dapibus leo.",
                                                        "_id": "5dadabe"
                                                    },
                                                    {
                                                        "tab_title": "3. Brisket bacon venison pig fatback kielbasa",
                                                        "tab_content": "Lorem ipsum dolor sit amet, consectetur adipiscing elit. Ut elit tellus, luctus nec ullamcorper mattis, pulvinar dapibus leo.",
                                                        "_id": "2405af0"
                                                    },
                                                    {
                                                        "tab_title": "4. Chicken venison turducken salami pig",
                                                        "tab_content": "Lorem ipsum dolor sit amet, consectetur adipiscing elit. Ut elit tellus, luctus nec ullamcorper mattis, pulvinar dapibus leo.",
                                                        "_id": "520f49a"
                                                    }
                                                ],
                                                "selected_icon": {
                                                    "value": "far fa-question-circle",
                                                    "library": "fa-regular"
                                                },
                                                "selected_active_icon": {
                                                    "value": "fas fa-chevron-up",
                                                    "library": "fa-solid"
                                                },
                                                "title_color": "#27272F",
                                                "tab_active_color": "#6AB42E",
                                                "title_typography_font_size_tablet": {
                                                    "unit": "px",
                                                    "size": 15,
                                                    "sizes": []
                                                },
                                                "title_typography_font_size_mobile": {
                                                    "unit": "px",
                                                    "size": 15,
                                                    "sizes": []
                                                },
                                                "title_typography_font_weight": "700",
                                                "title_typography_line_height_tablet": {
                                                    "unit": "em",
                                                    "size": 1.2,
                                                    "sizes": []
                                                },
                                                "title_typography_line_height_mobile": {
                                                    "unit": "em",
                                                    "size": 1.2,
                                                    "sizes": []
                                                },
                                                "icon_color": "#6AB42E",
                                                "icon_space": {
                                                    "unit": "px",
                                                    "size": 18,
                                                    "sizes": []
                                                },
                                                "__globals__": {
                                                    "icon_color": "globals\/colors?id=accent",
                                                    "title_color": "globals\/colors?id=primary",
                                                    "tab_active_color": "globals\/colors?id=accent",
                                                    "title_typography_typography": "",
                                                    "content_background_color": "",
                                                    "content_color": "",
                                                    "content_typography_typography": ""
                                                },
                                                "icon_align": "right"
                                            },
                                            "elements": [],
                                            "isInner": false,
                                            "widgetType": "toggle",
                                            "elType": "widget"
                                        }
                                    ],
                                    "isInner": true,
                                    "elType": "column"
                                },
                                {
                                    "id": "5f579531",
                                    "settings": {
                                        "_column_size": 50,
                                        "_inline_size": null,
                                        "_inline_size_tablet": 100
                                    },
                                    "elements": [
                                        {
                                            "id": "460074d7",
                                            "settings": {
                                                "tabs": [
                                                    {
                                                        "tab_title": "5. Bacon ipsum dolor amet venison",
                                                        "tab_content": "Lorem ipsum dolor sit amet, consectetur adipiscing elit. Ut elit tellus, luctus nec ullamcorper mattis, pulvinar dapibus leo.",
                                                        "_id": "63f635d"
                                                    },
                                                    {
                                                        "tab_title": "6. Hamburger boudin sirloin pancetta biltong ball tip",
                                                        "tab_content": "Lorem ipsum dolor sit amet, consectetur adipiscing elit. Ut elit tellus, luctus nec ullamcorper mattis, pulvinar dapibus leo.",
                                                        "_id": "5dadabe"
                                                    },
                                                    {
                                                        "tab_title": "7. Brisket bacon venison pig fatback kielbasa",
                                                        "tab_content": "Lorem ipsum dolor sit amet, consectetur adipiscing elit. Ut elit tellus, luctus nec ullamcorper mattis, pulvinar dapibus leo.",
                                                        "_id": "2405af0"
                                                    },
                                                    {
                                                        "tab_title": "8. Chicken venison turducken salami pig",
                                                        "tab_content": "Lorem ipsum dolor sit amet, consectetur adipiscing elit. Ut elit tellus, luctus nec ullamcorper mattis, pulvinar dapibus leo.",
                                                        "_id": "520f49a"
                                                    }
                                                ],
                                                "selected_icon": {
                                                    "value": "far fa-question-circle",
                                                    "library": "fa-regular"
                                                },
                                                "selected_active_icon": {
                                                    "value": "fas fa-chevron-up",
                                                    "library": "fa-solid"
                                                },
                                                "title_color": "#27272F",
                                                "tab_active_color": "#6AB42E",
                                                "title_typography_font_size_tablet": {
                                                    "unit": "px",
                                                    "size": 15,
                                                    "sizes": []
                                                },
                                                "title_typography_font_size_mobile": {
                                                    "unit": "px",
                                                    "size": 15,
                                                    "sizes": []
                                                },
                                                "title_typography_font_weight": "700",
                                                "title_typography_line_height_tablet": {
                                                    "unit": "em",
                                                    "size": 1.2,
                                                    "sizes": []
                                                },
                                                "title_typography_line_height_mobile": {
                                                    "unit": "em",
                                                    "size": 1.2,
                                                    "sizes": []
                                                },
                                                "icon_color": "#6AB42E",
                                                "icon_space": {
                                                    "unit": "px",
                                                    "size": 18,
                                                    "sizes": []
                                                },
                                                "__globals__": {
                                                    "icon_color": "globals\/colors?id=accent",
                                                    "title_color": "globals\/colors?id=primary",
                                                    "tab_active_color": "globals\/colors?id=accent",
                                                    "title_typography_typography": "",
                                                    "content_background_color": "",
                                                    "content_color": "",
                                                    "content_typography_typography": ""
                                                },
                                                "icon_align": "right"
                                            },
                                            "elements": [],
                                            "isInner": false,
                                            "widgetType": "toggle",
                                            "elType": "widget"
                                        }
                                    ],
                                    "isInner": true,
                                    "elType": "column"
                                }
                            ],
                            "isInner": true,
                            "elType": "section"
                        }
                    ],
                    "isInner": false,
                    "elType": "column"
                }
            ],
            "isInner": false,
            "elType": "section"
        }
    ]
}